LICENSE
MANIFEST.in
README
setup.py
sphinxcontrib/__init__.py
sphinxcontrib/jinjadomain.py
sphinxcontrib/autojinja/__init__.py
sphinxcontrib/autojinja/jinja.py
sphinxcontrib_jinjadomain.egg-info/PKG-INFO
sphinxcontrib_jinjadomain.egg-info/SOURCES.txt
sphinxcontrib_jinjadomain.egg-info/dependency_links.txt
sphinxcontrib_jinjadomain.egg-info/namespace_packages.txt
sphinxcontrib_jinjadomain.egg-info/not-zip-safe
sphinxcontrib_jinjadomain.egg-info/requires.txt
sphinxcontrib_jinjadomain.egg-info/top_level.txt