Metadata-Version: 1.1
Name: sphinxcontrib-jinjadomain
Version: 0.5.1
Summary: Jinja domain for jinja templates
Home-page: https://github.com/offlinehacker/sphinxcontrib.jinjadomain
Author: Jaka Hudoklin
Author-email: jakahudoklin@gmail.com
License: BSD
Download-URL: http://pypi.python.org/pypi/sphinxcontrib-jinjadomain
Platform: any
Classifier: Development Status :: 4 - Beta
Classifier: Environment :: Console
Classifier: Environment :: Web Environment
Classifier: Intended Audience :: Developers
Classifier: License :: OSI Approved :: BSD License
Classifier: Operating System :: OS Independent
Classifier: Programming Language :: Python
Classifier: Topic :: Documentation
Classifier: Topic :: Utilities
